multiselect/__init__.py
multiselect/multiselect_core.py
multiselect/multiselect_example.py
multiselect-0.1.0.dist-info/LICENSE
multiselect-0.1.0.dist-info/METADATA
multiselect-0.1.0.dist-info/WHEEL
multiselect-0.1.0.dist-info/top_level.txt
multiselect-0.1.0.dist-info/RECORD
