Metadata-Version: 2.1
Name: multiselect
Version: 0.1.0
Summary: A Python package for easy storing and manipulating with data coming from a multiselect dropdown menu
Home-page: https://github.com/DovaX/multiselect
Author: DovaX
Author-email: dovax.ai@gmail.com
License: UNKNOWN
Platform: UNKNOWN
Classifier: Programming Language :: Python :: 3
Classifier: License :: OSI Approved :: MIT License
Classifier: Operating System :: OS Independent
Requires-Python: >=3.6
